{
  "id": "19d982509287c0eb",
  "threadId": "19d982509287c0eb",
  "labelIds": [
    "UNREAD",
    "CATEGORY_UPDATES",
    "INBOX"
  ],
  "snippet": "Here&#39;s how to activate your new membership benefits Experian Membership ID# 10105455967061593 Sign In Your account is ready to roll First things first, Corey: lock your Experian credit file to",
  "payload": {
    "mimeType": "multipart/alternative",
    "headers": [
      {
        "name": "From",
        "value": "Experian \u003cwelcome@s.usa.experian.com\u003e"
      },
      {
        "name": "To",
        "value": "\u003ccbadcock@gmail.com\u003e"
      },
      {
        "name": "Subject",
        "value": "Corey, let's get you set up"
      },
      {
        "name": "Date",
        "value": "Thu, 16 Apr 2026 15:14:15 -0600"
      },
      {
        "name": "Reply-To",
        "value": "Experian \u003creply-64DOQU3JUDUEHHLUQSMXGL7QVU.70247@e.usa.experian.com\u003e"
      },
      {
        "name": "Message-ID",
        "value": "\u003ccfac893e-e092-476b-b52b-8415879801fc@atl1s07mta3210.xt.local\u003e"
      }
    ]
  },
  "sizeEstimate": 52580,
  "historyId": "16880934",
  "internalDate": "1776374055000"
}
